tvoverlord/__init__.py
tvoverlord/calendar.py
tvoverlord/client_finished.py
tvoverlord/config.ini
tvoverlord/config.py
tvoverlord/consoletable.py
tvoverlord/db.py
tvoverlord/downloadmanager.py
tvoverlord/history.py
tvoverlord/info.py
tvoverlord/location.py
tvoverlord/notify.py
tvoverlord/remote.py
tvoverlord/search.py
tvoverlord/show.py
tvoverlord/shows.py
tvoverlord/sync.py
tvoverlord/tracking.py
tvoverlord/tvol.py
tvoverlord/tvutil.py
tvoverlord/util.py
tvoverlord/search_providers/__init__.py
tvoverlord/search_providers/bitsnoop.py
tvoverlord/search_providers/btstorr_cc.py
tvoverlord/search_providers/example_search.py
tvoverlord/search_providers/extratorrent.py
tvoverlord/search_providers/eztv_ag.py
tvoverlord/search_providers/kickass_to.py
tvoverlord/search_providers/nzb.py
tvoverlord/search_providers/nzbclub_com.py
tvoverlord/search_providers/nzbindex_com.py
tvoverlord/search_providers/onethreethreesevenx_to.py
tvoverlord/search_providers/rarbg_to.py
tvoverlord/search_providers/thepiratebay_sx.py
tvoverlord/search_providers/torrentdownloads_me.py
tvoverlord-1.5.1.dist-info/DESCRIPTION.rst
tvoverlord-1.5.1.dist-info/METADATA
tvoverlord-1.5.1.dist-info/RECORD
tvoverlord-1.5.1.dist-info/WHEEL
tvoverlord-1.5.1.dist-info/entry_points.txt
tvoverlord-1.5.1.dist-info/metadata.json
tvoverlord-1.5.1.dist-info/top_level.txt
