Metadata-Version: 2.0
Name: tvoverlord
Version: 1.5.1
Summary: TV Overlord is a command line tool to download and manage TV shows from newsgroups or bittorent
Home-page: https://www.tvoverlord.com
Author: tvoverlord
Author-email: tvoverlord@mail.com
License: MIT
Platform: UNKNOWN
Classifier: Programming Language :: Python
Classifier: Programming Language :: Python :: 3
Classifier: Programming Language :: Python :: 3 :: Only
Classifier: Environment :: Console
Classifier: License :: OSI Approved :: GNU General Public License v3 (GPLv3)
Classifier: Operating System :: MacOS
Classifier: Operating System :: POSIX :: Linux
Classifier: Operating System :: Unix
Classifier: Operating System :: Microsoft :: Windows
Classifier: Topic :: Internet
Classifier: Topic :: Multimedia :: Video
Classifier: Natural Language :: English
Classifier: Development Status :: 5 - Production/Stable
Requires-Dist: tvdb-api (>=2.0)
Requires-Dist: beautifulsoup4
Requires-Dist: feedparser
Requires-Dist: requests
Requires-Dist: python-dateutil
Requires-Dist: click
Requires-Dist: colorama
